litner/__about__.py
litner/__init__.py
litner/arguments.py
litner/losses.py
litner/registry.py
litner/callbacks/__init__.py
litner/callbacks/logger.py
litner/datasets/__init__.py
litner/datasets/base.py
litner/datasets/iterable.py
litner/datasets/utils.py
litner/datasets/ner/__init__.py
litner/datasets/ner/base.py
litner/datasets/ner/cnn.py
litner/datasets/ner/crf.py
litner/datasets/ner/global_pointer.py
litner/datasets/ner/lear.py
litner/datasets/ner/mrc.py
litner/datasets/ner/span.py
litner/datasets/ner/tplinker.py
litner/datasets/ner/w2ner.py
litner/engines/__init__.py
litner/engines/base.py
litner/engines/ner.py
litner/layers/__init__.py
litner/layers/conv.py
litner/layers/crf.py
litner/layers/dropouts.py
litner/layers/global_pointer.py
litner/layers/layer_norm.py
litner/layers/lear.py
litner/layers/pfn.py
litner/layers/pooling.py
litner/layers/position.py
litner/layers/set_decoder.py
litner/layers/transformer.py
litner/layers/utils.py
litner/metrics/__init__.py
litner/metrics/base.py
litner/metrics/extraction/__init__.py
litner/metrics/extraction/precision_recall_fscore.py
litner/metrics/extraction/score.py
litner/metrics/extraction/span.py
litner/models/__init__.py
litner/models/base.py
litner/models/ner.py
litner/nn/__init__.py
litner/nn/decode_utils.py
litner/nn/model_utils.py
litner/nn/chinese_bert/__init__.py
litner/nn/chinese_bert/configuration_chinese_bert.py
litner/nn/chinese_bert/modeling_chinese_bert.py
litner/nn/chinese_bert/tokenization_chinesebert_fast.py
litner/nn/ner/__init__.py
litner/nn/ner/cnn.py
litner/nn/ner/crf.py
litner/nn/ner/global_pointer.py
litner/nn/ner/lear.py
litner/nn/ner/mrc.py
litner/nn/ner/span.py
litner/nn/ner/tplinker.py
litner/nn/ner/w2ner.py
litner/nn/roformer/__init__.py
litner/nn/roformer/configuration_roformer.py
litner/nn/roformer/modeling_roformer.py
litner/pipelines/__init__.py
litner/pipelines/base.py
litner/pipelines/ner.py
litner/pipelines/utils.py
litner/ui/__init__.py
litner/ui/ner.py
litner/ui/utils.py
litner-0.0.1.dist-info/LICENSE
litner-0.0.1.dist-info/METADATA
litner-0.0.1.dist-info/WHEEL
litner-0.0.1.dist-info/top_level.txt
litner-0.0.1.dist-info/RECORD
