Metadata-Version: 2.1
Name: litner
Version: 0.0.1
Summary: Pytorch-lightning Code Blocks for NER
Home-page: https://github.com/xusenlinzy/lit-ner
Author: xusenlin
Author-email: 1659821119@qq.com
License: UNKNOWN
Platform: UNKNOWN
Requires-Python: >=3.7
License-File: LICENSE
Requires-Dist: colorama
Requires-Dist: colorlog
Requires-Dist: datasets
Requires-Dist: jieba
Requires-Dist: pypinyin
Requires-Dist: pytorch-lightning
Requires-Dist: scikit-learn
Requires-Dist: scipy
Requires-Dist: seaborn
Requires-Dist: sentencepiece
Requires-Dist: setuptools
Requires-Dist: spacy
Requires-Dist: gradio
Requires-Dist: torchmetrics
Requires-Dist: transformers
